orders/__init__.py
orders/api_helper.py
orders/configuration.py
orders/orders_client.py
orders/controllers/__init__.py
orders/controllers/base_controller.py
orders/controllers/o_auth_authorization_controller.py
orders/controllers/orders_controller.py
orders/exceptions/__init__.py
orders/exceptions/api_exception.py
orders/exceptions/error_exception.py
orders/exceptions/o_auth_provider_exception.py
orders/http/__init__.py
orders/http/http_call_back.py
orders/http/http_method_enum.py
orders/http/http_request.py
orders/http/http_response.py
orders/http/auth/__init__.py
orders/http/auth/o_auth_2.py
orders/models/__init__.py
orders/models/activity_timestamps.py
orders/models/address.py
orders/models/amount_breakdown.py
orders/models/amount_with_breakdown.py
orders/models/apple_pay_attributes.py
orders/models/apple_pay_attributes_response.py
orders/models/apple_pay_card_response.py
orders/models/apple_pay_decrypted_token_data.py
orders/models/apple_pay_payment_data.py
orders/models/apple_pay_payment_data_type_enum.py
orders/models/apple_pay_payment_object.py
orders/models/apple_pay_request.py
orders/models/apple_pay_tokenized_card.py
orders/models/assurance_details.py
orders/models/authentication_response.py
orders/models/authorization.py
orders/models/authorization_incomplete_reason_enum.py
orders/models/authorization_status_details.py
orders/models/authorization_status_enum.py
orders/models/authorization_status_with_details.py
orders/models/authorization_with_additional_data.py
orders/models/avs_code_enum.py
orders/models/bancontact_payment_object.py
orders/models/bancontact_payment_request.py
orders/models/bin_details.py
orders/models/blik_experience_context.py
orders/models/blik_level_0_payment_object.py
orders/models/blik_one_click_payment_object.py
orders/models/blik_one_click_payment_request.py
orders/models/blik_payment_object.py
orders/models/blik_payment_request.py
orders/models/callback_configuration.py
orders/models/callback_events_enum.py
pp_api_sdk-1.0.0.dist-info/licenses/LICENSE
pp_api_sdk-1.0.0.dist-info/METADATA
pp_api_sdk-1.0.0.dist-info/WHEEL
pp_api_sdk-1.0.0.dist-info/top_level.txt
pp_api_sdk-1.0.0.dist-info/RECORD
