Metadata-Version: 2.4
Name: pp-api-sdk
Version: 1.0.0
Summary: The PayPal API is used to integrate PayPal's payment services into websites, mobile apps, and backend systems. It allows businesses, developers, and platforms to accept, process, and manage online payments securely and efficiently.
Author-email: Muhammad Hamza Shahzad <muhammad.hamza@apimatic.io>
Project-URL: Documentation, https://docs.apimatic.io/
Requires-Python: >=3.7
License-File: LICENSE
Requires-Dist: apimatic-core>=0.2.20,~=0.2.0
Requires-Dist: apimatic-core-interfaces>=0.1.5,~=0.1.0
Requires-Dist: apimatic-requests-client-adapter>=0.1.6,~=0.1.0
Provides-Extra: testutils
Requires-Dist: pytest>=7.2.2; extra == "testutils"
Dynamic: license-file
